{"py/object": "rasa_core.featurizers.MaxHistoryTrackerFeaturizer", "state_featurizer": {"py/object": "rasa_core.featurizers.BinarySingleStateFeaturizer", "num_features": 89, "input_state_map": {"entity_name": 26, "prev_action_chitchat": 83, "prev_utter_must_accept": 63, "slot_data_stored_0": 33, "entity_amount-of-money": 27, "prev_action_store_name": 84, "intent_ask_howdoing": 1, "entity_company": 24, "prev_action_store_job": 86, "intent_bye": 7, "intent_contact_sales": 9, "prev_utter_inform_privacypolicy": 50, "prev_action_store_budget": 81, "prev_utter_switch_dialogflow": 77, "prev_utter_cantsignup": 72, "intent_ask_whoisit": 6, "prev_utter_great": 67, "intent_how_to_get_started": 14, "intent_deny": 10, "entity_current_api": 30, "intent_ask_builder": 0, "prev_utter_quickstart": 74, "prev_utter_confirmationemail": 54, "prev_utter_noworries": 64, "prev_utter_ask_feedback": 73, "prev_utter_ask_company": 48, "prev_utter_contact_email": 57, "slot_subscribed_0": 37, "intent_canthelp": 8, "intent_signup_newsletter": 19, "prev_action_store_sales_info": 80, "prev_utter_sales_contact": 55, "prev_utter_ask_businessmail": 44, "prev_utter_ask_goal": 49, "prev_utter_greet": 42, "prev_action_subscribe_newsletter": 79, "prev_utter_confirm_salesrequest": 52, "prev_utter_ask_jobfunction": 45, "prev_utter_docu": 53, "prev_action_pause": 88, "intent_enter_data": 11, "prev_action_default_fallback": 41, "prev_utter_moreinformation": 51, "prev_utter_out_of_scope": 59, "prev_utter_switch_luis": 78, "slot_company_name_0": 32, "intent_ask_whatspossible": 5, "entity_email": 25, "prev_action_store_usecase": 82, "prev_utter_canthelp": 69, "prev_utter_thank_usecase": 68, "prev_utter_thumbsup": 71, "slot_email_0": 34, "intent_ask_isbot": 2, "prev_utter_ask_usecase": 43, "entity_number": 28, "slot_use_case_0": 38, "prev_utter_bye": 65, "prev_utter_possibilities": 60, "intent_new_project": 17, "entity_value": 29, "intent_greet": 13, "intent_technical_question": 21, "prev_utter_awesome": 66, "prev_utter_already_subscribed": 56, "prev_utter_quickstart_nlu_only": 75, "prev_utter_ask_budget": 47, "intent_mood_confirm": 16, "prev_utter_no_speak": 58, "intent_ask_weather": 3, "slot_job_function_0": 35, "prev_action_restart": 40, "intent_human_handoff": 15, "slot_budget_0": 31, "prev_utter_nohelp": 70, "intent_switch": 20, "prev_utter_ask_name": 61, "prev_utter_ask_email": 46, "prev_action_store_email": 87, "prev_action_store_company": 85, "entity_jobfunction": 23, "intent_feedback": 12, "intent_out_of_scope": 18, "slot_person_name_0": 36, "prev_utter_ask_migration": 76, "prev_action_listen": 39, "intent_ask_whatisrasa": 4, "intent_thank": 22, "prev_utter_change_mind": 62}, "user_feature_len": 31, "slot_feature_len": 8}, "max_history": 5, "use_intent_probabilities": false, "remove_duplicates": true}